redis_json_dict/__init__.py
redis_json_dict/_version.py
redis_json_dict/_version.pyi
redis_json_dict/py.typed
redis_json_dict/redis_json_dict.py
redis_json_dict-0.2.1.dist-info/METADATA
redis_json_dict-0.2.1.dist-info/WHEEL
redis_json_dict-0.2.1.dist-info/licenses/LICENSE
redis_json_dict-0.2.1.dist-info/RECORD
